asma_package/__init__.py
asma_package/example.py
asma_package-0.1.0.dist-info/LICENSE
asma_package-0.1.0.dist-info/METADATA
asma_package-0.1.0.dist-info/WHEEL
asma_package-0.1.0.dist-info/top_level.txt
asma_package-0.1.0.dist-info/RECORD
