Metadata-Version: 2.1
Name: asma_package
Version: 0.1.0
Summary: A brief description of your package
Author: Asma Shahid
Author-email: Asma Shahid <asma.shahid@datumlabs.io>
License: MIT
Classifier: Programming Language :: Python :: 3
Classifier: License :: OSI Approved :: MIT License
Classifier: Operating System :: OS Independent
Requires-Python: <4,>=3.6
License-File: LICENSE
